dapla_auth_client/__init__.py
dapla_auth_client/auth.py
dapla_auth_client/const.py
dapla_auth_client/py.typed
dapla_auth_client-1.2.5.dist-info/METADATA
dapla_auth_client-1.2.5.dist-info/WHEEL
dapla_auth_client-1.2.5.dist-info/entry_points.txt
dapla_auth_client-1.2.5.dist-info/licenses/LICENSE
dapla_auth_client-1.2.5.dist-info/RECORD
