Metadata-Version: 2.4
Name: dapla-auth-client
Version: 1.2.5
Summary: Dapla Auth Client
Project-URL: Homepage, https://github.com/statisticsnorway/dapla-auth-client
Project-URL: Repository, https://github.com/statisticsnorway/dapla-auth-client
Project-URL: Documentation, https://statisticsnorway.github.io/dapla-auth-client
Project-URL: Changelog, https://github.com/statisticsnorway/dapla-auth-client/releases
Author-email: Dapla Developers <dapla-platform-developers@ssb.no>
License-Expression: MIT
License-File: LICENSE
Classifier: Development Status :: 5 - Production/Stable
Requires-Python: >=3.10
Requires-Dist: deprecated>=1.2.18
Requires-Dist: google-auth>=2.40.2
Requires-Dist: requests>=2.27.1
Requires-Dist: responses>=0.24.0
Requires-Dist: types-deprecated>=1.2.15.20250304
Requires-Dist: types-requests>=2.28.11
